setup.py
bdz_util/__init__.py
bdz_util/http_util/__init__.py
bdz_util/http_util/http_session.py
bdz_util/str_util/__init__.py
bdz_util/str_util/string_util.py
rule_spider/__init__.py
rule_spider.egg-info/PKG-INFO
rule_spider.egg-info/SOURCES.txt
rule_spider.egg-info/dependency_links.txt
rule_spider.egg-info/requires.txt
rule_spider.egg-info/top_level.txt
rule_spider/config/__init__.py
rule_spider/manager/__init__.py
rule_spider/manager/admin.py
rule_spider/model/__init__.py
rule_spider/orm/__init__.py
rule_spider/parser/__init__.py
rule_spider/rule/__init__.py
rule_spider/runner/__init__.py