Metadata-Version: 1.0
Name: rule-spider
Version: 0.0.1
Summary: 常用工具类
Home-page: http://github.com/badaozhai
Author: chenjian
Author-email: goudanbaba123@gmail.com
License: MIT Licence
Keywords: pip,util,bdz_util,httpclient,spider,rule
Platform: any
